TensorflowCong0Dao1/README.md
TensorflowCong0Dao1/__init__.py
TensorflowCong0Dao1/__main__.py
TensorflowCong0Dao1/file.epub
TensorflowCong0Dao1/index.html
TensorflowCong0Dao1/css/__init__.py
TensorflowCong0Dao1/css/annotations.css
TensorflowCong0Dao1/css/main.css
TensorflowCong0Dao1/css/normalize.css
TensorflowCong0Dao1/css/popup.css
TensorflowCong0Dao1/font/__init__.py
TensorflowCong0Dao1/font/fontello.eot
TensorflowCong0Dao1/font/fontello.svg
TensorflowCong0Dao1/font/fontello.ttf
TensorflowCong0Dao1/font/fontello.woff
TensorflowCong0Dao1/img/__init__.py
TensorflowCong0Dao1/img/annotator-glyph-sprite.png
TensorflowCong0Dao1/img/annotator-icon-sprite.png
TensorflowCong0Dao1/img/apple-touch-icon.png
TensorflowCong0Dao1/img/cancelfullscreen.png
TensorflowCong0Dao1/img/close.png
TensorflowCong0Dao1/img/fullscreen.png
TensorflowCong0Dao1/img/loader.gif
TensorflowCong0Dao1/img/menu-icon.png
TensorflowCong0Dao1/img/save.png
TensorflowCong0Dao1/img/saved.png
TensorflowCong0Dao1/img/settings-s.png
TensorflowCong0Dao1/img/settings.png
TensorflowCong0Dao1/img/star.png
TensorflowCong0Dao1/js/__init__.py
TensorflowCong0Dao1/js/epub.js
TensorflowCong0Dao1/js/epub.min.js
TensorflowCong0Dao1/js/epub.min.map
TensorflowCong0Dao1/js/hooks.min.js
TensorflowCong0Dao1/js/hooks.min.map
TensorflowCong0Dao1/js/reader.js
TensorflowCong0Dao1/js/reader.js.map
TensorflowCong0Dao1/js/reader.min.js
TensorflowCong0Dao1/js/reader.min.map
TensorflowCong0Dao1/js/hooks/__init__.py
TensorflowCong0Dao1/js/hooks/extensions/__init__.py
TensorflowCong0Dao1/js/hooks/extensions/highlight.js
TensorflowCong0Dao1/js/libs/__init__.py
TensorflowCong0Dao1/js/libs/jquery.min.js
TensorflowCong0Dao1/js/libs/localforage.min.js
TensorflowCong0Dao1/js/libs/screenfull.js
TensorflowCong0Dao1/js/libs/screenfull.min.js
TensorflowCong0Dao1/js/libs/zip.min.js
TensorflowCong0Dao1/js/plugins/__init__.py
TensorflowCong0Dao1/js/plugins/hypothesis.js
TensorflowCong0Dao1/js/plugins/search.js
tensorflow_cong_0_dao_1-2024.3.3.0.dist-info/METADATA
tensorflow_cong_0_dao_1-2024.3.3.0.dist-info/WHEEL
tensorflow_cong_0_dao_1-2024.3.3.0.dist-info/entry_points.txt
tensorflow_cong_0_dao_1-2024.3.3.0.dist-info/top_level.txt
tensorflow_cong_0_dao_1-2024.3.3.0.dist-info/RECORD
